README.rst
setup.cfg
setup.py
logen/__init__.py
logen/client.py
logen_trace.egg-info/PKG-INFO
logen_trace.egg-info/SOURCES.txt
logen_trace.egg-info/dependency_links.txt
logen_trace.egg-info/not-zip-safe
logen_trace.egg-info/requires.txt
logen_trace.egg-info/top_level.txt