Metadata-Version: 1.1
Name: logen-trace
Version: 0.1.0
Summary: Delivery confirmation for Logen(https://www.ilogen.com)
Home-page: https://github.com/perhapsspy/logen-trace
Author: PerhapsSPY
Author-email: perhapsspy@gmail.com
License: MIT
Platform: UNKNOWN
Classifier: Development Status :: 2 - Pre-Alpha
Classifier: Environment :: Web Environment
Classifier: Intended Audience :: Developers
Classifier: License :: OSI Approved :: MIT License
Classifier: Operating System :: OS Independent
Classifier: Programming Language :: Python
Classifier: Programming Language :: Python :: 2
Classifier: Programming Language :: Python :: 2.7
Classifier: Topic :: Software Development :: Libraries :: Python Modules
